water_benchmark_hub/VERSION
water_benchmark_hub/__init__.py
water_benchmark_hub/benchmark_resource.py
water_benchmark_hub/benchmarks.py
water_benchmark_hub/database.json
water_benchmark_hub/meta_data.py
water_benchmark_hub/metrics.py
water_benchmark_hub/batadal/__init__.py
water_benchmark_hub/batadal/batadal.py
water_benchmark_hub/batadal/batadal_data.py
water_benchmark_hub/battledim/__init__.py
water_benchmark_hub/battledim/battledim.py
water_benchmark_hub/battledim/battledim_data.py
water_benchmark_hub/bwdf/__init__.py
water_benchmark_hub/bwdf/bwdf.py
water_benchmark_hub/gecco_waterquality/__init__.py
water_benchmark_hub/gecco_waterquality/gecco_water_quality.py
water_benchmark_hub/gym/__init__.py
water_benchmark_hub/gym/scenario_control_env.py
water_benchmark_hub/leak_testbed/__init__.py
water_benchmark_hub/leak_testbed/leak_testbed.py
water_benchmark_hub/leakdb/__init__.py
water_benchmark_hub/leakdb/leakdb.py
water_benchmark_hub/leakdb/leakdb_data.py
water_benchmark_hub/leakg3pd/__init__.py
water_benchmark_hub/leakg3pd/leakg3pd.py
water_benchmark_hub/leakg3pd/leakg3pd_data.py
water_benchmark_hub/networks/__init__.py
water_benchmark_hub/networks/bwsn_networks.py
water_benchmark_hub/networks/epanet_examples.py
water_benchmark_hub/networks/ltown.py
water_benchmark_hub/networks/networks.py
water_benchmark_hub/water_usage/__init__.py
water_benchmark_hub/water_usage/water_usage.py
water_benchmark_hub-0.3.1.dist-info/licenses/LICENSE
water_benchmark_hub-0.3.1.dist-info/METADATA
water_benchmark_hub-0.3.1.dist-info/WHEEL
water_benchmark_hub-0.3.1.dist-info/top_level.txt
water_benchmark_hub-0.3.1.dist-info/RECORD
