Metadata-Version: 2.4
Name: water-benchmark-hub
Version: 0.3.1
Summary: WaterBenchmarkHub
Author-email: André Artelt <aartelt@techfak.uni-bielefeld.de>
License-Expression: MIT
Project-URL: Homepage, https://github.com/WaterFutures/WaterBenchmarkHub
Project-URL: Documentation, https://water-benchmark-hub.readthedocs.io/en/latest/
Project-URL: Repository, https://github.com/WaterFutures/WaterBenchmarkHub.git
Project-URL: Issues, https://github.com/WaterFutures/WaterBenchmarkHub/issues
Keywords: water,networks,benchmarks,data
Classifier: Development Status :: 4 - Beta
Classifier: Intended Audience :: Science/Research
Classifier: Programming Language :: Python :: 3
Classifier: Programming Language :: Python :: 3.9
Classifier: Programming Language :: Python :: 3.10
Classifier: Programming Language :: Python :: 3.11
Classifier: Programming Language :: Python :: 3.12
Classifier: Programming Language :: Python :: 3.13
Requires-Python: >=3.9
License-File: LICENSE
Requires-Dist: epyt-flow>=0.10
Requires-Dist: wf4bwdf>=1.0.0
Dynamic: license-file
